help_generator/__init__.py
help_generator/help_generator.py
help_generator-0.1.1.dist-info/LICENSE
help_generator-0.1.1.dist-info/METADATA
help_generator-0.1.1.dist-info/WHEEL
help_generator-0.1.1.dist-info/top_level.txt
help_generator-0.1.1.dist-info/RECORD
