Metadata-Version: 2.1
Name: help-generator
Version: 0.1.1
Summary: Source code help generator
Author: Johan Hagelbäck
Author-email: johan.hagelback@gmail.com
License-File: LICENSE
